iofx-0.1.1.dist-info/METADATA
iofx-0.1.1.dist-info/WHEEL
iofx-0.1.1.dist-info/licenses/LICENSE
iofx/__init__.py
iofx/detect.py
iofx/param.py
iofx-0.1.1.dist-info/RECORD
